README.rst
setup.py
django_filmmap.egg-info/PKG-INFO
django_filmmap.egg-info/SOURCES.txt
django_filmmap.egg-info/dependency_links.txt
django_filmmap.egg-info/top_level.txt
filmmap/__init__.py
filmmap/admin.py
filmmap/models.py
filmmap/tests.py
filmmap/urls.py
filmmap/views.py
filmmap/management/__init__.py
filmmap/management/commands/__init__.py
filmmap/management/commands/update_films.py
filmmap/utils/__init__.py
filmmap/utils/fields.py
uber/__init__.py
uber/settings.py
uber/urls.py
uber/wsgi.py